docs/conf.py
ifiscripts-2024.10.9.data/data/26_XYZ-22_Rec709.cube
ifiscripts-2024.10.9.data/data/film_scan_aip_documentation.txt
ifiscripts-2024.10.9.data/scripts/Objects.py
ifiscripts-2024.10.9.data/scripts/accession_register.py
ifiscripts-2024.10.9.data/scripts/aipcreator.py
ifiscripts-2024.10.9.data/scripts/as11fixity.py
ifiscripts-2024.10.9.data/scripts/batchaipcreator.py
ifiscripts-2024.10.9.data/scripts/batchdiff_framemd5.py
ifiscripts-2024.10.9.data/scripts/batchmakeshell.py
ifiscripts-2024.10.9.data/scripts/batchsc_aip_update.py
ifiscripts-2024.10.9.data/scripts/batchsc_checkdir.py
ifiscripts-2024.10.9.data/scripts/batchsc_organise.py
ifiscripts-2024.10.9.data/scripts/batchsc_validate.py
ifiscripts-2024.10.9.data/scripts/batchsipcreator.py
ifiscripts-2024.10.9.data/scripts/batchvalidate.py
ifiscripts-2024.10.9.data/scripts/bitc.py
ifiscripts-2024.10.9.data/scripts/check_register.py
ifiscripts-2024.10.9.data/scripts/concat.py
ifiscripts-2024.10.9.data/scripts/copyit.py
ifiscripts-2024.10.9.data/scripts/dcdm_helperpbcore.py
ifiscripts-2024.10.9.data/scripts/dcpaccess.py
ifiscripts-2024.10.9.data/scripts/dcpfixity.py
ifiscripts-2024.10.9.data/scripts/deletefiles.py
ifiscripts-2024.10.9.data/scripts/dfxml.py
ifiscripts-2024.10.9.data/scripts/durationcheck.py
ifiscripts-2024.10.9.data/scripts/ffv1mkvvalidate.py
ifiscripts-2024.10.9.data/scripts/framemd5.py
ifiscripts-2024.10.9.data/scripts/get_ps_list.py
ifiscripts-2024.10.9.data/scripts/getdip.py
ifiscripts-2024.10.9.data/scripts/ififuncs.py
ifiscripts-2024.10.9.data/scripts/loopline_repackage.py
ifiscripts-2024.10.9.data/scripts/lossy_check.py
ifiscripts-2024.10.9.data/scripts/make_mediaconch.py
ifiscripts-2024.10.9.data/scripts/makedfxml.py
ifiscripts-2024.10.9.data/scripts/makedip.py
ifiscripts-2024.10.9.data/scripts/makeffv1.py
ifiscripts-2024.10.9.data/scripts/makepbcore.py
ifiscripts-2024.10.9.data/scripts/makeuuid.py
ifiscripts-2024.10.9.data/scripts/makezip.py
ifiscripts-2024.10.9.dist-info/LICENSE.txt
ifiscripts-2024.10.9.dist-info/METADATA
ifiscripts-2024.10.9.dist-info/WHEEL
ifiscripts-2024.10.9.dist-info/top_level.txt
ifiscripts-2024.10.9.dist-info/RECORD
