Metadata-Version: 2.1
Name: ifiscripts
Version: 2024.10.9
Summary: Scripts for processing moving image material in the Irish Film Institute/Irish Film Archive
Author: Kieran O'Leary
Author-email: Kieran O'Leary <kieran.o.leary@gmail.com>
License: MIT License
Project-URL: Homepage, https://github.com/Irish-Film-Institute/IFIscripts
Project-URL: Bug Tracker, https://github.com/Irish-Film-Institute/IFIscripts/issues
Classifier: Programming Language :: Python :: 3.8
Classifier: Programming Language :: Python :: 3.9
Classifier: Programming Language :: Python :: 3.10
Classifier: Programming Language :: Python :: 3.11
Classifier: Programming Language :: Python :: 3.12
Classifier: License :: OSI Approved :: MIT License
Classifier: Operating System :: OS Independent
Requires-Python: >=3.8
License-File: LICENSE.txt
Requires-Dist: lxml
Requires-Dist: bagit
Requires-Dist: dicttoxml
Requires-Dist: future
Requires-Dist: clairmeta
Requires-Dist: psutil
Requires-Dist: unidecode
